fastapiPypiMiddle/__init__.py
fastapiPypiMiddle/constants.py
fastapiPypiMiddle/middleware.py
fastapiPypiMiddle/otel.py
fastapi_pipy_middleware-0.1.7.dist-info/METADATA
fastapi_pipy_middleware-0.1.7.dist-info/WHEEL
fastapi_pipy_middleware-0.1.7.dist-info/top_level.txt
fastapi_pipy_middleware-0.1.7.dist-info/RECORD
