Metadata-Version: 2.1
Name: fastapi-pipy-middleware
Version: 0.1.7
Summary: A FastAPI middleware example
Home-page: https://pypi.org/manage/projects/fastapi-pipy-middleware
Author: Your Name
Author-email: your.email@example.com
Requires-Dist: fastapi
Requires-Dist: starlette
